tridu33ml/__init__.py
tridu33ml/nn/__init__.py
tridu33ml/nn/core.py
tridu33ml/utils/__init__.py
tridu33ml/utils/utilities.py
tridu33ml-0.0.1.dist-info/LICENSE
tridu33ml-0.0.1.dist-info/METADATA
tridu33ml-0.0.1.dist-info/WHEEL
tridu33ml-0.0.1.dist-info/top_level.txt
tridu33ml-0.0.1.dist-info/RECORD
