Metadata-Version: 2.1
Name: tridu33ml
Version: 0.0.1
Summary: tridu33 Learn Write ML Frame
Home-page: UNKNOWN
Author: Tridu33
Author-email: tridu33@qq.com
License: UNKNOWN
Platform: UNKNOWN
Classifier: Programming Language :: Python :: 3
Classifier: License :: OSI Approved :: MIT License
Classifier: Operating System :: OS Independent
Requires-Python: >=3.6
